axisvm/__init__.py
axisvm/com/__init__.py
axisvm/com/attr.py
axisvm/com/axapp.py
axisvm/com/axcalculation.py
axisvm/com/axcatalog.py
axisvm/com/axdomain.py
axisvm/com/axline.py
axisvm/com/axloadcombinations.py
axisvm/com/axmaterial.py
axisvm/com/axmember.py
axisvm/com/axmodel.py
axisvm/com/axnodalsupports.py
axisvm/com/axnode.py
axisvm/com/axrcbeamdesign.py
axisvm/com/axresult.py
axisvm/com/axsurface.py
axisvm/com/axwindow.py
axisvm/com/client.py
axisvm/com/tlb.py
axisvm/com/core/__init__.py
axisvm/com/core/abc.py
axisvm/com/core/utils.py
axisvm/com/core/wrap.py
axisvm/docs/__init__.py
axisvm/docs/utils.py
axisvm/examples/__init__.py
axisvm/examples/downloads.py
axisvm-1.2.2.dist-info/LICENSE
axisvm-1.2.2.dist-info/METADATA
axisvm-1.2.2.dist-info/WHEEL
axisvm-1.2.2.dist-info/top_level.txt
axisvm-1.2.2.dist-info/RECORD
