Metadata-Version: 2.1
Name: axisvm
Version: 1.2.2
Summary: A Python package for AxisVM.
Author-email: "InterCAD Ltd." <gbokor@axisvm.eu>
Maintainer-email: "InterCAD Ltd." <gbokor@axisvm.eu>
License: MIT License
Project-URL: Homepage, https://github.com/AxisVM/pyaxisvm
Keywords: engineering,mechanics,finite element method,AxisVM,civil engineering,steel design,concrete design,timber design
Classifier: Development Status :: 5 - Production/Stable
Classifier: License :: OSI Approved :: MIT License
Classifier: Programming Language :: Python :: 3.7
Classifier: Programming Language :: Python :: 3.8
Classifier: Programming Language :: Python :: 3.9
Classifier: Programming Language :: Python :: 3.10
Classifier: Programming Language :: Python :: 3 :: Only
Classifier: Operating System :: Microsoft :: Windows :: Windows 10
Classifier: Operating System :: Microsoft :: Windows :: Windows 11
Requires-Python: <3.12,>=3.10
License-File: LICENSE
Requires-Dist: setuptools >=65.5.1
Requires-Dist: wheel >=0.38.0
Requires-Dist: pywin32
Requires-Dist: appdirs
Requires-Dist: sigmaepsilon.mesh <3.0,>=2.0.0
Requires-Dist: comtypes ==1.1.11
Requires-Dist: ipython
Requires-Dist: pyvista
Requires-Dist: pandas
Provides-Extra: dev
Requires-Dist: flake8 ; extra == 'dev'
Requires-Dist: ipykernel ; extra == 'dev'
Provides-Extra: docs
Requires-Dist: ipython ; extra == 'docs'
Requires-Dist: myst-parser ; extra == 'docs'
Requires-Dist: memory-profiler ; extra == 'docs'
Requires-Dist: nbsphinx ; extra == 'docs'
Requires-Dist: sphinx-gallery ; extra == 'docs'
Requires-Dist: sphinx-copybutton ; extra == 'docs'
Requires-Dist: sphinxcontrib-bibtex ; extra == 'docs'
Requires-Dist: nbsphinx-link ; extra == 'docs'
Requires-Dist: sphinxcontrib-svg2pdfconverter ; extra == 'docs'
Requires-Dist: sphinx-design ; extra == 'docs'
Requires-Dist: sphinx-inline-tabs ; extra == 'docs'
Requires-Dist: pydata-sphinx-theme ; extra == 'docs'
Requires-Dist: sphinx-plotly-directive ; extra == 'docs'
Requires-Dist: networkx ; extra == 'docs'
Requires-Dist: plotly ; extra == 'docs'
Requires-Dist: nbformat ; extra == 'docs'
Requires-Dist: pypdfium2 ; extra == 'docs'
Requires-Dist: matplotlib ; extra == 'docs'
Requires-Dist: setuptools >=65.5.1 ; extra == 'docs'
Requires-Dist: numpy >=1.22.2 ; extra == 'docs'
Requires-Dist: pillow >=10.0.1 ; extra == 'docs'
Requires-Dist: tornado >=6.3.3 ; extra == 'docs'
Provides-Extra: test
Requires-Dist: pytest ; extra == 'test'
Requires-Dist: pytest-cov ; extra == 'test'
Requires-Dist: testbook ; extra == 'test'
Requires-Dist: ipykernel ; extra == 'test'
